{
	"song": {
		"player1": "bf",
		"player2": "daspook",
		"notes": [
			{
				"lengthInSteps": 16,
				"sectionNotes": [
					[
						0,
						6,
						0
					],
					[
						136.363632,
						7,
						0
					],
					[
						272.727264,
						5,
						0
					],
					[
						409.090881,
						4,
						0
					],
					[
						545.4545,
						2,
						0
					],
					[
						681.8182,
						3,
						0
					],
					[
						818.181763,
						1,
						0
					],
					[
						954.5454,
						0,
						0
					],
					[
						818.181818181818,
						2,
						0,
						"Hurt Note"
					]
				],
				"mustHitSection": true
			},
			{
				"lengthInSteps": 16,
				"sectionNotes": [
					[
						1090.909,
						7,
						0
					],
					[
						1090.909,
						3,
						0
					],
					[
						1227.27271,
						4,
						0
					],
					[
						1227.27271,
						0,
						0
					],
					[
						1363.63635,
						1,
						0
					],
					[
						1363.63635,
						5,
						0
					],
					[
						1500,
						0,
						0
					],
					[
						1500,
						4,
						0
					],
					[
						1636.36353,
						1,
						0
					],
					[
						1636.36353,
						5,
						0
					],
					[
						1772.72717,
						2,
						0
					],
					[
						1772.72717,
						6,
						0
					],
					[
						1909.09082,
						4,
						272.727264
					],
					[
						1909.09082,
						0,
						272.727264
					],
					[
						1909.09090909091,
						3,
						0,
						"Hurt Note"
					]
				],
				"mustHitSection": true
			},
			{
				"lengthInSteps": 16,
				"sectionNotes": [
					[
						2181.818,
						3,
						0
					],
					[
						2250,
						0,
						0
					],
					[
						2318.18164,
						3,
						0
					],
					[
						2386.36353,
						0,
						0
					],
					[
						2454.54541,
						2,
						0
					],
					[
						2522.72729,
						3,
						0
					],
					[
						2590.909,
						0,
						0
					],
					[
						2659.09082,
						1,
						0
					],
					[
						2727.27271,
						2,
						0
					],
					[
						2795.45435,
						3,
						0
					],
					[
						2863.63623,
						1,
						0
					],
					[
						2931.818,
						0,
						0
					],
					[
						3000,
						2,
						0
					],
					[
						3068.18164,
						3,
						0
					],
					[
						3136.36353,
						2,
						0
					],
					[
						3204.54541,
						0,
						0
					]
				],
				"mustHitSection": false,
				"camerabounce": true
			},
			{
				"lengthInSteps": 16,
				"sectionNotes": [
					[
						3272.727,
						3,
						0
					],
					[
						3340.909,
						3,
						0
					],
					[
						3409.09082,
						0,
						0
					],
					[
						3477.27271,
						0,
						0
					],
					[
						3545.45435,
						3,
						0
					],
					[
						3613.63623,
						0,
						0
					],
					[
						3681.818,
						2,
						0
					],
					[
						3750,
						3,
						0
					],
					[
						3818.18164,
						0,
						0
					],
					[
						3886.36353,
						3,
						0
					],
					[
						3954.54541,
						0,
						0
					],
					[
						4022.727,
						2,
						0
					],
					[
						4090.909,
						3,
						0
					],
					[
						4159.091,
						3,
						0
					],
					[
						4227.27246,
						0,
						0
					],
					[
						4295.45459,
						0,
						0
					]
				],
				"mustHitSection": false
			},
			{
				"lengthInSteps": 16,
				"sectionNotes": [
					[
						4363.636,
						0,
						0
					],
					[
						4500,
						1,
						0
					],
					[
						4636.36328,
						0,
						0
					],
					[
						4772.727,
						3,
						0
					],
					[
						4909.091,
						0,
						0
					],
					[
						5045.45459,
						2,
						0
					],
					[
						5181.818,
						1,
						0
					],
					[
						5318.18164,
						0,
						0
					]
				],
				"mustHitSection": false
			},
			{
				"lengthInSteps": 16,
				"sectionNotes": [
					[
						5454.54541,
						3,
						0
					],
					[
						5590.90869,
						0,
						0
					],
					[
						5727.27246,
						1,
						0
					],
					[
						5863.636,
						0,
						0
					],
					[
						6000,
						1,
						0
					],
					[
						6136.36328,
						0,
						0
					],
					[
						6272.727,
						3,
						0
					],
					[
						6409.091,
						0,
						0
					]
				],
				"mustHitSection": false
			},
			{
				"lengthInSteps": 16,
				"sectionNotes": [
					[
						6545.454,
						3,
						0
					],
					[
						6613.636,
						0,
						0
					],
					[
						6681.818,
						3,
						0
					],
					[
						6750,
						0,
						0
					],
					[
						6818.18164,
						2,
						0
					],
					[
						6886.36328,
						3,
						0
					],
					[
						6954.54541,
						0,
						0
					],
					[
						7022.727,
						1,
						0
					],
					[
						7090.90869,
						2,
						0
					],
					[
						7159.091,
						3,
						0
					],
					[
						7227.27246,
						1,
						0
					],
					[
						7295.454,
						0,
						0
					],
					[
						7363.636,
						2,
						0
					],
					[
						7431.818,
						3,
						0
					],
					[
						7500,
						2,
						0
					],
					[
						7568.18164,
						0,
						0
					],
					[
						7295.45454545455,
						3,
						0,
						"Hurt Note"
					]
				],
				"mustHitSection": true
			},
			{
				"lengthInSteps": 16,
				"sectionNotes": [
					[
						7636.36328,
						3,
						0
					],
					[
						7704.54541,
						3,
						0
					],
					[
						7772.727,
						0,
						0
					],
					[
						7840.90869,
						0,
						0
					],
					[
						7909.091,
						3,
						0
					],
					[
						7977.27246,
						0,
						0
					],
					[
						8045.454,
						2,
						0
					],
					[
						8113.636,
						3,
						0
					],
					[
						8181.818,
						0,
						0
					],
					[
						8250,
						3,
						0
					],
					[
						8318.182,
						0,
						0
					],
					[
						8386.363,
						2,
						0
					],
					[
						8454.545,
						3,
						0
					],
					[
						8522.727,
						3,
						0
					],
					[
						8590.909,
						0,
						0
					],
					[
						8659.091,
						0,
						0
					],
					[
						8659.09090909091,
						2,
						0,
						"Hurt Note"
					]
				],
				"mustHitSection": true
			},
			{
				"lengthInSteps": 16,
				"sectionNotes": [
					[
						8727.272,
						0,
						0
					],
					[
						8863.636,
						1,
						0
					],
					[
						9000,
						0,
						0
					],
					[
						9136.363,
						3,
						0
					],
					[
						9272.727,
						0,
						0
					],
					[
						9409.091,
						2,
						0
					],
					[
						9545.454,
						1,
						0
					],
					[
						9681.818,
						0,
						0
					]
				],
				"mustHitSection": true
			},
			{
				"lengthInSteps": 16,
				"sectionNotes": [
					[
						9818.182,
						3,
						0
					],
					[
						9954.545,
						0,
						0
					],
					[
						10090.9092,
						1,
						0
					],
					[
						10227.2725,
						0,
						0
					],
					[
						10363.6357,
						1,
						0
					],
					[
						10500,
						0,
						0
					],
					[
						10636.3633,
						3,
						0
					],
					[
						10772.7266,
						0,
						0
					],
					[
						10772.7272727273,
						1,
						0,
						"Hurt Note"
					]
				],
				"mustHitSection": true
			},
			{
				"lengthInSteps": 16,
				"sectionNotes": [
					[
						10909.0908,
						0,
						1090.909
					]
				],
				"mustHitSection": false
			},
			{
				"lengthInSteps": 16,
				"sectionNotes": [
					[
						12000,
						1,
						818.181763
					],
					[
						12818.1816,
						3,
						272.727264
					]
				],
				"mustHitSection": false
			},
			{
				"lengthInSteps": 16,
				"sectionNotes": [
					[
						13090.9082,
						0,
						1090.909
					]
				],
				"mustHitSection": false
			},
			{
				"lengthInSteps": 16,
				"sectionNotes": [
					[
						14181.8174,
						0,
						818.181763
					],
					[
						15000,
						2,
						272.727264
					]
				],
				"mustHitSection": false
			},
			{
				"lengthInSteps": 16,
				"sectionNotes": [
					[
						15272.7266,
						4,
						1090.909
					],
					[
						15272.7266,
						0,
						1090.909
					],
					[
						15545.4545454546,
						2,
						0,
						"Hurt Note"
					],
					[
						15886.3636363636,
						3,
						0,
						"Hurt Note"
					],
					[
						16090.9090909091,
						1,
						0,
						"Hurt Note"
					]
				],
				"mustHitSection": true
			},
			{
				"lengthInSteps": 16,
				"sectionNotes": [
					[
						16363.6357,
						5,
						1090.909
					],
					[
						16363.6357,
						1,
						818.181763
					],
					[
						17181.8184,
						3,
						272.727264
					],
					[
						17386.3636363636,
						0,
						0,
						"Alt Animation"
					],
					[
						16568.1818181818,
						2,
						0,
						"Hurt Note"
					],
					[
						16840.9090909091,
						3,
						0,
						"Hurt Note"
					],
					[
						17045.4545454546,
						0,
						0,
						"Hurt Note"
					],
					[
						17318.1818181818,
						2,
						0,
						"Hurt Note"
					]
				],
				"mustHitSection": true
			},
			{
				"lengthInSteps": 16,
				"sectionNotes": [
					[
						17454.5449,
						4,
						1090.909
					],
					[
						17454.5449,
						0,
						1090.909
					],
					[
						17522.7272727273,
						2,
						0,
						"Hurt Note"
					],
					[
						17863.6363636364,
						2,
						0,
						"Hurt Note"
					],
					[
						18136.3636363636,
						3,
						0,
						"Hurt Note"
					],
					[
						18409.0909090909,
						2,
						0,
						"Hurt Note"
					]
				],
				"mustHitSection": true
			},
			{
				"lengthInSteps": 16,
				"sectionNotes": [
					[
						18545.4531,
						6,
						1090.909
					],
					[
						18545.4531,
						0,
						818.181763
					],
					[
						19363.6367,
						2,
						272.727264
					],
					[
						18681.8181818182,
						1,
						0,
						"Hurt Note"
					],
					[
						18954.5454545455,
						3,
						0,
						"Hurt Note"
					],
					[
						19159.0909090909,
						2,
						0,
						"Hurt Note"
					],
					[
						19431.8181818182,
						3,
						0,
						"Hurt Note"
					],
					[
						19500,
						0,
						0,
						"Hurt Note"
					]
				],
				"mustHitSection": true
			},
			{
				"lengthInSteps": 16,
				"sectionNotes": [
					[
						19636.3633,
						0,
						0
					],
					[
						19704.5449,
						3,
						0
					],
					[
						19772.7266,
						1,
						0
					],
					[
						19840.9082,
						0,
						0
					],
					[
						19909.09,
						2,
						0
					],
					[
						19977.2715,
						0,
						0
					],
					[
						20045.4531,
						3,
						0
					],
					[
						20113.6367,
						1,
						0
					],
					[
						20181.8184,
						2,
						0
					],
					[
						20250,
						0,
						0
					],
					[
						20318.1816,
						3,
						0
					],
					[
						20386.3633,
						2,
						0
					],
					[
						20454.5449,
						1,
						0
					],
					[
						20522.7266,
						0,
						0
					],
					[
						20590.9082,
						1,
						0
					],
					[
						20659.09,
						2,
						0
					]
				],
				"mustHitSection": false
			},
			{
				"lengthInSteps": 16,
				"sectionNotes": [
					[
						20727.2715,
						3,
						0
					],
					[
						20863.6348,
						0,
						0
					],
					[
						21000,
						3,
						0
					],
					[
						21136.3633,
						0,
						0
					],
					[
						21272.7266,
						2,
						0
					],
					[
						21409.09,
						0,
						0
					],
					[
						21545.4531,
						3,
						0
					],
					[
						21681.8184,
						2,
						0
					]
				],
				"mustHitSection": false
			},
			{
				"lengthInSteps": 16,
				"sectionNotes": [
					[
						21818.1816,
						0,
						0
					],
					[
						21886.3633,
						3,
						0
					],
					[
						21954.5449,
						1,
						0
					],
					[
						22022.7266,
						0,
						0
					],
					[
						22090.9082,
						2,
						0
					],
					[
						22159.09,
						0,
						0
					],
					[
						22227.2715,
						3,
						0
					],
					[
						22295.4531,
						1,
						0
					],
					[
						22363.6348,
						2,
						0
					],
					[
						22431.8184,
						0,
						0
					],
					[
						22500,
						3,
						0
					],
					[
						22568.1816,
						2,
						0
					],
					[
						22636.3633,
						1,
						0
					],
					[
						22704.5449,
						0,
						0
					],
					[
						22772.7266,
						1,
						0
					],
					[
						22840.9082,
						2,
						0
					],
					[
						22431.8181818182,
						1,
						0,
						"Hurt Note"
					]
				],
				"mustHitSection": true
			},
			{
				"lengthInSteps": 16,
				"sectionNotes": [
					[
						22909.09,
						3,
						0
					],
					[
						23045.4531,
						0,
						0
					],
					[
						23181.8184,
						3,
						0
					],
					[
						23318.1816,
						0,
						0
					],
					[
						23454.5449,
						2,
						0
					],
					[
						23590.9082,
						0,
						0
					],
					[
						23727.2715,
						3,
						0
					],
					[
						23863.6348,
						2,
						0
					],
					[
						23863.6363636364,
						0,
						0,
						"Hurt Note"
					]
				],
				"mustHitSection": true
			},
			{
				"lengthInSteps": 16,
				"sectionNotes": [
					[
						24000,
						0,
						0
					],
					[
						24136.3633,
						1,
						0
					],
					[
						24272.7266,
						0,
						0
					],
					[
						24340.9082,
						1,
						0
					],
					[
						24409.09,
						0,
						0
					],
					[
						24477.2715,
						2,
						0
					],
					[
						24545.4531,
						0,
						0
					],
					[
						24613.6348,
						1,
						0
					],
					[
						24681.8184,
						0,
						0
					],
					[
						24750,
						1,
						0
					],
					[
						24818.1816,
						2,
						0
					],
					[
						24886.3633,
						0,
						0
					],
					[
						24954.5449,
						1,
						0
					],
					[
						25022.7266,
						0,
						0
					]
				],
				"mustHitSection": false
			},
			{
				"lengthInSteps": 16,
				"sectionNotes": [
					[
						25090.9082,
						3,
						0
					],
					[
						25159.09,
						0,
						0
					],
					[
						25227.2715,
						1,
						0
					],
					[
						25295.4531,
						0,
						0
					],
					[
						25363.6348,
						3,
						0
					],
					[
						25431.8184,
						2,
						0
					],
					[
						25500,
						1,
						0
					],
					[
						25568.1816,
						0,
						0
					],
					[
						25636.3633,
						2,
						0
					],
					[
						25704.5449,
						3,
						0
					],
					[
						25772.7266,
						2,
						0
					],
					[
						25840.9082,
						0,
						0
					],
					[
						25909.09,
						3,
						0
					],
					[
						25977.2715,
						2,
						0
					],
					[
						26045.4531,
						0,
						0
					],
					[
						26113.6348,
						1,
						0
					]
				],
				"mustHitSection": false
			},
			{
				"lengthInSteps": 16,
				"sectionNotes": [
					[
						26181.8164,
						0,
						0
					],
					[
						26318.1816,
						1,
						0
					],
					[
						26454.5449,
						0,
						0
					],
					[
						26522.7266,
						1,
						0
					],
					[
						26590.9082,
						0,
						0
					],
					[
						26659.09,
						2,
						0
					],
					[
						26727.2715,
						0,
						0
					],
					[
						26795.4531,
						1,
						0
					],
					[
						26863.6348,
						0,
						0
					],
					[
						26931.8164,
						1,
						0
					],
					[
						27000,
						2,
						0
					],
					[
						27068.1816,
						0,
						0
					],
					[
						27136.3633,
						1,
						0
					],
					[
						27204.5449,
						0,
						0
					],
					[
						26386.3636363637,
						3,
						0,
						"Hurt Note"
					],
					[
						26727.2727272727,
						3,
						0,
						"Hurt Note"
					],
					[
						26863.6363636364,
						3,
						0,
						"Hurt Note"
					],
					[
						27136.3636363637,
						3,
						0,
						"Hurt Note"
					]
				],
				"mustHitSection": true
			},
			{
				"lengthInSteps": 16,
				"sectionNotes": [
					[
						27272.7266,
						3,
						0
					],
					[
						27340.9082,
						0,
						0
					],
					[
						27409.09,
						1,
						0
					],
					[
						27477.2715,
						0,
						0
					],
					[
						27545.4531,
						3,
						0
					],
					[
						27613.6348,
						2,
						0
					],
					[
						27681.8164,
						1,
						0
					],
					[
						27750,
						0,
						0
					],
					[
						27818.1816,
						2,
						0
					],
					[
						27886.3633,
						3,
						0
					],
					[
						27954.5449,
						2,
						0
					],
					[
						28022.7266,
						0,
						0
					],
					[
						28090.9082,
						3,
						0
					],
					[
						28159.09,
						2,
						0
					],
					[
						28227.2715,
						0,
						0
					],
					[
						28295.4531,
						1,
						0
					],
					[
						27886.3636363637,
						0,
						0,
						"Hurt Note"
					]
				],
				"mustHitSection": true
			},
			{
				"lengthInSteps": 16,
				"sectionNotes": [
					[
						28363.6348,
						0,
						0
					],
					[
						28431.8164,
						2,
						0
					],
					[
						28500,
						0,
						0
					],
					[
						28568.1816,
						3,
						0
					],
					[
						28636.3633,
						2,
						0
					],
					[
						28704.5449,
						3,
						0
					],
					[
						28772.7266,
						0,
						0
					],
					[
						28840.9082,
						2,
						0
					],
					[
						28909.09,
						3,
						0
					],
					[
						28977.2715,
						2,
						0
					],
					[
						29045.4531,
						0,
						0
					],
					[
						29113.6348,
						2,
						0
					],
					[
						29181.8164,
						3,
						0
					],
					[
						29250,
						2,
						0
					],
					[
						29318.1816,
						3,
						0
					],
					[
						29386.3633,
						1,
						0
					]
				],
				"mustHitSection": false
			},
			{
				"lengthInSteps": 16,
				"sectionNotes": [
					[
						29454.5449,
						2,
						0
					],
					[
						29522.7266,
						2,
						0
					],
					[
						29590.9082,
						1,
						0
					],
					[
						29659.09,
						1,
						0
					],
					[
						29727.2715,
						0,
						0
					],
					[
						29795.4531,
						0,
						0
					],
					[
						29863.6348,
						2,
						0
					],
					[
						29931.8164,
						3,
						0
					],
					[
						30000,
						0,
						0
					],
					[
						30068.1816,
						1,
						0
					],
					[
						30136.3633,
						0,
						0
					],
					[
						30204.5449,
						3,
						0
					],
					[
						30272.7266,
						2,
						0
					],
					[
						30340.9082,
						3,
						0
					],
					[
						30409.09,
						0,
						0
					],
					[
						30477.2715,
						1,
						0
					]
				],
				"mustHitSection": false
			},
			{
				"lengthInSteps": 16,
				"sectionNotes": [
					[
						30545.4531,
						0,
						0
					],
					[
						30613.6348,
						2,
						0
					],
					[
						30681.8164,
						0,
						0
					],
					[
						30750,
						3,
						0
					],
					[
						30818.1816,
						2,
						0
					],
					[
						30886.3633,
						3,
						0
					],
					[
						30954.5449,
						0,
						0
					],
					[
						31022.7266,
						2,
						0
					],
					[
						31090.9082,
						3,
						0
					],
					[
						31159.09,
						2,
						0
					],
					[
						31227.2715,
						0,
						0
					],
					[
						31295.4531,
						2,
						0
					],
					[
						31363.6348,
						3,
						0
					],
					[
						31431.8164,
						2,
						0
					],
					[
						31500,
						3,
						0
					],
					[
						31568.1816,
						1,
						0
					],
					[
						31363.6363636364,
						0,
						0,
						"Hurt Note"
					]
				],
				"mustHitSection": true
			},
			{
				"lengthInSteps": 16,
				"sectionNotes": [
					[
						31636.3633,
						2,
						0
					],
					[
						31704.5449,
						2,
						0
					],
					[
						31772.7266,
						1,
						0
					],
					[
						31840.9082,
						1,
						0
					],
					[
						31909.09,
						0,
						0
					],
					[
						31977.2715,
						0,
						0
					],
					[
						32045.4531,
						2,
						0
					],
					[
						32113.6348,
						3,
						0
					],
					[
						32181.8164,
						0,
						0
					],
					[
						32249.998,
						1,
						0
					],
					[
						32318.1816,
						0,
						0
					],
					[
						32386.3633,
						3,
						0
					],
					[
						32454.5449,
						2,
						0
					],
					[
						32522.7266,
						3,
						0
					],
					[
						32590.9082,
						0,
						0
					],
					[
						32659.09,
						1,
						0
					],
					[
						31909.0909090909,
						3,
						0,
						"Hurt Note"
					]
				],
				"mustHitSection": true
			},
			{
				"lengthInSteps": 16,
				"sectionNotes": [
					[
						32727.2715,
						0,
						0
					],
					[
						32795.4531,
						3,
						0
					],
					[
						32863.6367,
						2,
						0
					],
					[
						32931.8164,
						0,
						0
					],
					[
						33000,
						3,
						0
					],
					[
						33068.18,
						0,
						0
					],
					[
						33136.3633,
						2,
						0
					],
					[
						33204.543,
						3,
						0
					],
					[
						33272.7266,
						1,
						0
					],
					[
						33340.9063,
						3,
						0
					],
					[
						33409.09,
						0,
						0
					],
					[
						33477.2734,
						3,
						0
					],
					[
						33545.4531,
						2,
						0
					],
					[
						33613.6367,
						1,
						0
					],
					[
						33681.8164,
						2,
						0
					],
					[
						33750,
						0,
						0
					]
				],
				"mustHitSection": false
			},
			{
				"lengthInSteps": 16,
				"sectionNotes": [
					[
						33818.18,
						3,
						0
					],
					[
						33886.3633,
						0,
						0
					],
					[
						33954.543,
						2,
						0
					],
					[
						34022.7266,
						0,
						0
					],
					[
						34090.9063,
						1,
						0
					],
					[
						34159.09,
						2,
						0
					],
					[
						34227.2734,
						2,
						0
					],
					[
						34295.4531,
						0,
						0
					],
					[
						34363.6367,
						2,
						0
					],
					[
						34431.8164,
						0,
						0
					],
					[
						34500,
						1,
						0
					],
					[
						34568.18,
						3,
						0
					],
					[
						34636.3633,
						0,
						0
					],
					[
						34704.543,
						2,
						0
					],
					[
						34772.7266,
						1,
						0
					],
					[
						34840.9063,
						2,
						0
					]
				],
				"mustHitSection": false
			},
			{
				"lengthInSteps": 16,
				"sectionNotes": [
					[
						34909.09,
						0,
						0
					],
					[
						34977.2734,
						2,
						0
					],
					[
						35045.4531,
						0,
						0
					],
					[
						35113.6367,
						2,
						0
					],
					[
						35181.8164,
						0,
						0
					],
					[
						35318.18,
						3,
						0
					],
					[
						35454.543,
						1,
						0
					],
					[
						35590.9063,
						0,
						0
					],
					[
						35727.2734,
						2,
						0
					],
					[
						35863.6367,
						2,
						0
					]
				],
				"mustHitSection": false
			},
			{
				"lengthInSteps": 16,
				"sectionNotes": [
					[
						36000,
						0,
						0
					],
					[
						36136.3633,
						3,
						0
					],
					[
						36272.7266,
						1,
						0
					],
					[
						36409.09,
						2,
						0
					],
					[
						36545.4531,
						2,
						0
					],
					[
						36681.8164,
						0,
						0
					],
					[
						36818.18,
						3,
						0
					],
					[
						36954.543,
						1,
						0
					]
				],
				"mustHitSection": false
			},
			{
				"lengthInSteps": 16,
				"sectionNotes": [
					[
						37090.9063,
						0,
						0
					],
					[
						37227.2734,
						3,
						0
					],
					[
						37363.6367,
						2,
						0
					],
					[
						37500,
						2,
						0
					],
					[
						37636.3633,
						0,
						0
					],
					[
						37772.7266,
						2,
						0
					],
					[
						37909.09,
						2,
						0
					],
					[
						38045.4531,
						1,
						0
					]
				],
				"mustHitSection": false
			},
			{
				"lengthInSteps": 16,
				"sectionNotes": [
					[
						38181.8164,
						0,
						0
					],
					[
						38318.18,
						1,
						0
					],
					[
						38454.543,
						2,
						0
					],
					[
						38590.9063,
						0,
						0
					],
					[
						38727.2734,
						2,
						0
					],
					[
						38863.6367,
						2,
						0
					],
					[
						39000,
						0,
						0
					],
					[
						39136.3633,
						3,
						0
					]
				],
				"mustHitSection": false
			},
			{
				"lengthInSteps": 16,
				"sectionNotes": [
					[
						39272.7266,
						1,
						0
					],
					[
						39409.09,
						3,
						0
					],
					[
						39545.4531,
						1,
						0
					],
					[
						39681.8164,
						0,
						0
					],
					[
						39818.18,
						1,
						0
					],
					[
						39954.543,
						2,
						0
					],
					[
						40090.9063,
						1,
						0
					],
					[
						40227.2734,
						2,
						0
					]
				],
				"mustHitSection": false
			},
			{
				"lengthInSteps": 16,
				"sectionNotes": [
					[
						40363.6367,
						2,
						0
					],
					[
						40431.8164,
						2,
						0
					],
					[
						40500,
						3,
						0
					],
					[
						40568.18,
						1,
						0
					],
					[
						40636.3633,
						3,
						0
					],
					[
						40704.543,
						1,
						0
					],
					[
						40772.7266,
						2,
						0
					],
					[
						40840.9063,
						2,
						0
					],
					[
						40909.09,
						3,
						0
					],
					[
						40977.27,
						1,
						0
					],
					[
						41045.4531,
						2,
						0
					],
					[
						41113.6367,
						3,
						0
					],
					[
						41181.8164,
						0,
						0
					],
					[
						41250,
						3,
						0
					],
					[
						41318.18,
						2,
						0
					],
					[
						41386.3633,
						0,
						0
					]
				],
				"mustHitSection": false
			},
			{
				"lengthInSteps": 16,
				"sectionNotes": [
					[
						41454.543,
						0,
						0
					],
					[
						41522.7266,
						3,
						0
					],
					[
						41590.9063,
						2,
						0
					],
					[
						41659.09,
						0,
						0
					],
					[
						41727.27,
						3,
						0
					],
					[
						41795.4531,
						0,
						0
					],
					[
						41863.6367,
						2,
						0
					],
					[
						41931.8164,
						3,
						0
					],
					[
						42000,
						1,
						0
					],
					[
						42068.18,
						3,
						0
					],
					[
						42136.3633,
						0,
						0
					],
					[
						42204.543,
						3,
						0
					],
					[
						42272.7266,
						2,
						0
					],
					[
						42340.9063,
						1,
						0
					],
					[
						42409.09,
						2,
						0
					],
					[
						42477.27,
						0,
						0
					],
					[
						42136.3636363636,
						2,
						0,
						"Hurt Note"
					]
				],
				"mustHitSection": true
			},
			{
				"lengthInSteps": 16,
				"sectionNotes": [
					[
						42545.4531,
						3,
						0
					],
					[
						42613.6367,
						0,
						0
					],
					[
						42681.8164,
						2,
						0
					],
					[
						42750,
						0,
						0
					],
					[
						42818.18,
						1,
						0
					],
					[
						42886.3633,
						2,
						0
					],
					[
						42954.543,
						2,
						0
					],
					[
						43022.7266,
						0,
						0
					],
					[
						43090.9063,
						2,
						0
					],
					[
						43159.09,
						0,
						0
					],
					[
						43227.27,
						1,
						0
					],
					[
						43295.4531,
						3,
						0
					],
					[
						43363.6367,
						0,
						0
					],
					[
						43431.8164,
						2,
						0
					],
					[
						43500,
						1,
						0
					],
					[
						43568.18,
						2,
						0
					],
					[
						43568.1818181818,
						0,
						0,
						"Hurt Note"
					]
				],
				"mustHitSection": true
			},
			{
				"lengthInSteps": 16,
				"sectionNotes": [
					[
						43636.3633,
						0,
						0
					],
					[
						43704.543,
						2,
						0
					],
					[
						43772.7266,
						0,
						0
					],
					[
						43840.9063,
						2,
						0
					],
					[
						43909.09,
						0,
						0
					],
					[
						44045.4531,
						3,
						0
					],
					[
						44181.8164,
						1,
						0
					],
					[
						44318.18,
						0,
						0
					],
					[
						44454.543,
						2,
						0
					],
					[
						44590.9063,
						2,
						0
					],
					[
						44318.1818181818,
						3,
						0,
						"Hurt Note"
					]
				],
				"mustHitSection": true
			},
			{
				"lengthInSteps": 16,
				"sectionNotes": [
					[
						44727.27,
						0,
						0
					],
					[
						44863.6367,
						3,
						0
					],
					[
						45000,
						1,
						0
					],
					[
						45136.3633,
						2,
						0
					],
					[
						45272.7266,
						2,
						0
					],
					[
						45409.09,
						0,
						0
					],
					[
						45545.4531,
						3,
						0
					],
					[
						45681.8164,
						1,
						0
					],
					[
						45681.8181818182,
						0,
						0,
						"Hurt Note"
					]
				],
				"mustHitSection": true
			},
			{
				"lengthInSteps": 16,
				"sectionNotes": [
					[
						45818.18,
						0,
						0
					],
					[
						45954.543,
						3,
						0
					],
					[
						46090.9063,
						2,
						0
					],
					[
						46227.27,
						2,
						0
					],
					[
						46363.6367,
						0,
						0
					],
					[
						46500,
						2,
						0
					],
					[
						46636.3633,
						2,
						0
					],
					[
						46772.7266,
						1,
						0
					],
					[
						46500,
						1,
						0,
						"Hurt Note"
					]
				],
				"mustHitSection": true
			},
			{
				"lengthInSteps": 16,
				"sectionNotes": [
					[
						46909.09,
						0,
						0
					],
					[
						47045.4531,
						1,
						0
					],
					[
						47181.8164,
						2,
						0
					],
					[
						47318.18,
						0,
						0
					],
					[
						47454.543,
						2,
						0
					],
					[
						47590.9063,
						2,
						0
					],
					[
						47727.27,
						0,
						0
					],
					[
						47863.6367,
						3,
						0
					],
					[
						47863.6363636364,
						0,
						0,
						"Hurt Note"
					]
				],
				"mustHitSection": true
			},
			{
				"lengthInSteps": 16,
				"sectionNotes": [
					[
						48000,
						1,
						0
					],
					[
						48136.3633,
						3,
						0
					],
					[
						48272.7266,
						1,
						0
					],
					[
						48409.09,
						0,
						0
					],
					[
						48545.4531,
						1,
						0
					],
					[
						48681.8164,
						2,
						0
					],
					[
						48818.18,
						1,
						0
					],
					[
						48954.543,
						2,
						0
					],
					[
						48818.1818181818,
						3,
						0,
						"Hurt Note"
					]
				],
				"mustHitSection": true
			},
			{
				"lengthInSteps": 16,
				"sectionNotes": [
					[
						49090.9063,
						2,
						0
					],
					[
						49159.09,
						2,
						0
					],
					[
						49227.27,
						3,
						0
					],
					[
						49295.4531,
						1,
						0
					],
					[
						49363.6367,
						3,
						0
					],
					[
						49431.8164,
						1,
						0
					],
					[
						49500,
						2,
						0
					],
					[
						49568.18,
						2,
						0
					],
					[
						49636.3633,
						3,
						0
					],
					[
						49704.543,
						1,
						0
					],
					[
						49772.7266,
						2,
						0
					],
					[
						49840.9063,
						3,
						0
					],
					[
						49909.09,
						0,
						0
					],
					[
						49977.27,
						3,
						0
					],
					[
						50045.4531,
						2,
						0
					],
					[
						50113.6367,
						0,
						0
					]
				],
				"mustHitSection": true
			},
			{
				"lengthInSteps": 16,
				"sectionNotes": [
					[
						50181.8164,
						0,
						0
					],
					[
						50181.8164,
						6,
						1090.909
					],
					[
						50250,
						1,
						0
					],
					[
						50318.18,
						3,
						0
					],
					[
						50386.3633,
						1,
						0
					],
					[
						50454.543,
						0,
						136.363632
					],
					[
						50590.9063,
						1,
						136.363632
					],
					[
						50727.27,
						3,
						136.363632
					],
					[
						50863.6367,
						0,
						136.363632
					],
					[
						51000,
						3,
						136.363632
					],
					[
						51136.3633,
						1,
						136.363632
					],
					[
						50454.5454545454,
						5,
						0,
						"Hurt Note"
					],
					[
						50863.6363636363,
						4,
						0,
						"Hurt Note"
					],
					[
						51068.1818181818,
						7,
						0,
						"Hurt Note"
					]
				],
				"mustHitSection": false
			},
			{
				"lengthInSteps": 16,
				"sectionNotes": [
					[
						51272.7266,
						4,
						545.4545
					],
					[
						51272.7266,
						0,
						0
					],
					[
						51340.9063,
						1,
						0
					],
					[
						51409.09,
						3,
						0
					],
					[
						51477.27,
						2,
						0
					],
					[
						51545.4531,
						3,
						136.363632
					],
					[
						51681.8164,
						2,
						136.363632
					],
					[
						51818.18,
						7,
						545.4545
					],
					[
						51818.18,
						3,
						136.363632
					],
					[
						51954.543,
						2,
						136.363632
					],
					[
						52090.9063,
						1,
						136.363632
					],
					[
						52227.27,
						0,
						136.363632
					],
					[
						51545.4545454545,
						6,
						0,
						"Hurt Note"
					],
					[
						51954.5454545454,
						4,
						0,
						"Hurt Note"
					],
					[
						52090.9090909091,
						6,
						0,
						"Hurt Note"
					]
				],
				"mustHitSection": false
			},
			{
				"lengthInSteps": 16,
				"sectionNotes": [
					[
						52363.6328,
						6,
						1090.909
					],
					[
						52363.6328,
						0,
						0
					],
					[
						52431.8164,
						1,
						0
					],
					[
						52500,
						3,
						0
					],
					[
						52568.18,
						1,
						0
					],
					[
						52636.3633,
						0,
						136.363632
					],
					[
						52772.7266,
						1,
						136.363632
					],
					[
						52909.09,
						3,
						136.363632
					],
					[
						53045.4531,
						0,
						136.363632
					],
					[
						53181.8164,
						3,
						136.363632
					],
					[
						53318.18,
						1,
						136.363632
					],
					[
						52772.7272727273,
						2,
						0,
						"Hurt Note"
					]
				],
				"mustHitSection": true
			},
			{
				"lengthInSteps": 16,
				"sectionNotes": [
					[
						53454.543,
						4,
						545.4545
					],
					[
						53454.543,
						0,
						0
					],
					[
						53522.7266,
						1,
						0
					],
					[
						53590.9063,
						3,
						0
					],
					[
						53659.09,
						2,
						0
					],
					[
						53727.27,
						3,
						136.363632
					],
					[
						53863.6328,
						2,
						136.363632
					],
					[
						54000,
						7,
						545.4545
					],
					[
						54000,
						3,
						136.363632
					],
					[
						54136.3633,
						2,
						136.363632
					],
					[
						54272.7266,
						1,
						136.363632
					],
					[
						54409.09,
						0,
						136.363632
					],
					[
						54272.7272727272,
						0,
						0,
						"Hurt Note"
					]
				],
				"mustHitSection": true
			},
			{
				"lengthInSteps": 16,
				"sectionNotes": [
					[
						54545.4531,
						3,
						0
					],
					[
						54613.6328,
						0,
						0
					],
					[
						54681.8164,
						1,
						0
					],
					[
						54750,
						0,
						0
					],
					[
						54818.18,
						3,
						0
					],
					[
						54886.3633,
						0,
						0
					],
					[
						54954.543,
						2,
						0
					],
					[
						55022.7266,
						0,
						0
					],
					[
						55090.9063,
						3,
						0
					],
					[
						55159.09,
						2,
						0
					],
					[
						55227.27,
						1,
						0
					],
					[
						55295.4531,
						0,
						0
					],
					[
						55363.6328,
						3,
						0
					],
					[
						55431.8164,
						0,
						0
					],
					[
						55500,
						2,
						0
					],
					[
						55568.18,
						0,
						0
					]
				],
				"mustHitSection": false
			},
			{
				"lengthInSteps": 16,
				"sectionNotes": [
					[
						55636.3633,
						7,
						0
					],
					[
						55704.543,
						4,
						0
					],
					[
						55772.7266,
						5,
						0
					],
					[
						55840.9063,
						4,
						0
					],
					[
						55909.09,
						7,
						0
					],
					[
						55977.27,
						4,
						0
					],
					[
						56045.4531,
						6,
						0
					],
					[
						56113.6328,
						4,
						0
					],
					[
						56181.8164,
						7,
						0
					],
					[
						56250,
						6,
						0
					],
					[
						56318.18,
						5,
						0
					],
					[
						56386.3633,
						4,
						0
					],
					[
						56454.543,
						7,
						0
					],
					[
						56522.7266,
						4,
						0
					],
					[
						56590.9063,
						6,
						0
					],
					[
						56659.09,
						4,
						0
					]
				],
				"mustHitSection": false
			},
			{
				"lengthInSteps": 16,
				"sectionNotes": [
					[
						56727.27,
						3,
						0
					],
					[
						56727.27,
						7,
						0
					],
					[
						56795.4531,
						0,
						0
					],
					[
						56795.4531,
						4,
						0
					],
					[
						56863.6328,
						6,
						0
					],
					[
						56863.6328,
						2,
						0
					],
					[
						56931.8164,
						5,
						0
					],
					[
						56931.8164,
						1,
						0
					],
					[
						57000,
						3,
						0
					],
					[
						57000,
						7,
						0
					],
					[
						57068.18,
						2,
						0
					],
					[
						57068.18,
						6,
						0
					],
					[
						57136.3633,
						0,
						0
					],
					[
						57136.3633,
						4,
						0
					],
					[
						57204.543,
						1,
						0
					],
					[
						57204.543,
						5,
						0
					],
					[
						57272.7266,
						2,
						0
					],
					[
						57272.7266,
						6,
						0
					],
					[
						57340.9063,
						3,
						0
					],
					[
						57340.9063,
						7,
						0
					],
					[
						57409.09,
						2,
						0
					],
					[
						57409.09,
						6,
						0
					],
					[
						57477.27,
						1,
						0
					],
					[
						57477.27,
						5,
						0
					],
					[
						57545.4531,
						3,
						0
					],
					[
						57545.4531,
						7,
						0
					],
					[
						57613.6328,
						1,
						0
					],
					[
						57613.6328,
						5,
						0
					],
					[
						57681.8164,
						0,
						0
					],
					[
						57681.8164,
						4,
						0
					],
					[
						57750,
						2,
						0
					],
					[
						57750,
						6,
						0
					]
				],
				"mustHitSection": true
			},
			{
				"lengthInSteps": 16,
				"sectionNotes": [
					[
						57818.18,
						3,
						0
					],
					[
						57818.18,
						7,
						0
					],
					[
						57886.3633,
						5,
						0
					],
					[
						57886.3633,
						1,
						0
					],
					[
						57954.543,
						0,
						0
					],
					[
						57954.543,
						4,
						0
					],
					[
						58022.7266,
						1,
						0
					],
					[
						58022.7266,
						5,
						0
					],
					[
						58090.9063,
						0,
						0
					],
					[
						58090.9063,
						4,
						0
					],
					[
						58159.09,
						5,
						0
					],
					[
						58159.09,
						1,
						0
					],
					[
						58227.27,
						7,
						0
					],
					[
						58227.27,
						3,
						0
					],
					[
						58295.4531,
						2,
						0
					],
					[
						58295.4531,
						6,
						0
					],
					[
						58363.6328,
						0,
						0
					],
					[
						58363.6328,
						4,
						0
					],
					[
						58431.8164,
						5,
						0
					],
					[
						58431.8164,
						1,
						0
					],
					[
						58500,
						4,
						0
					],
					[
						58500,
						4,
						0
					],
					[
						58500,
						0,
						0
					],
					[
						58500,
						0,
						0
					],
					[
						58568.18,
						2,
						0
					],
					[
						58568.18,
						6,
						0
					],
					[
						58636.3633,
						0,
						0
					],
					[
						58636.3633,
						4,
						0
					],
					[
						58704.543,
						6,
						0
					],
					[
						58704.543,
						2,
						0
					],
					[
						58772.7266,
						7,
						0
					],
					[
						58772.7266,
						3,
						0
					],
					[
						58840.9063,
						6,
						0
					],
					[
						58840.9063,
						2,
						0
					]
				],
				"mustHitSection": true
			},
			{
				"lengthInSteps": 16,
				"sectionNotes": [
					[
						58909.09,
						2,
						272.727264
					],
					[
						59181.8164,
						1,
						272.727264
					],
					[
						59454.543,
						0,
						272.727264
					],
					[
						59727.27,
						1,
						136.363632
					],
					[
						59863.6328,
						2,
						136.363632
					]
				],
				"mustHitSection": false
			},
			{
				"lengthInSteps": 16,
				"sectionNotes": [
					[
						60000,
						2,
						272.727264
					],
					[
						60000,
						4,
						272.727264
					],
					[
						60272.7266,
						1,
						272.727264
					],
					[
						60545.4531,
						0,
						272.727264
					],
					[
						60818.18,
						1,
						136.363632
					],
					[
						60954.543,
						2,
						136.363632
					]
				],
				"mustHitSection": true
			},
			{
				"lengthInSteps": 16,
				"sectionNotes": [
					[
						61090.9063,
						4,
						272.727264
					],
					[
						61090.9063,
						3,
						272.727264
					],
					[
						61363.6328,
						2,
						272.727264
					],
					[
						61636.3633,
						0,
						272.727264
					],
					[
						61909.09,
						1,
						136.363632
					],
					[
						62045.4531,
						0,
						136.363632
					]
				],
				"mustHitSection": false
			},
			{
				"lengthInSteps": 16,
				"sectionNotes": [
					[
						62181.8164,
						7,
						272.727264
					],
					[
						62181.8164,
						3,
						272.727264
					],
					[
						62454.543,
						2,
						272.727264
					],
					[
						62727.27,
						0,
						272.727264
					],
					[
						63000,
						1,
						136.363632
					],
					[
						63136.3633,
						0,
						136.363632
					]
				],
				"mustHitSection": true
			},
			{
				"lengthInSteps": 16,
				"sectionNotes": [
					[
						63272.7266,
						7,
						272.727264
					],
					[
						63272.7266,
						2,
						272.727264
					],
					[
						63545.4531,
						3,
						272.727264
					],
					[
						63818.18,
						1,
						272.727264
					],
					[
						64090.9063,
						0,
						272.727264
					]
				],
				"mustHitSection": false
			},
			{
				"lengthInSteps": 16,
				"sectionNotes": [
					[
						64363.6328,
						6,
						272.727264
					],
					[
						64363.6328,
						2,
						272.727264
					],
					[
						64636.3633,
						3,
						272.727264
					],
					[
						64909.09,
						1,
						272.727264
					],
					[
						65181.8164,
						0,
						272.727264
					]
				],
				"mustHitSection": true
			},
			{
				"lengthInSteps": 16,
				"sectionNotes": [
					[
						65454.543,
						7,
						136.363632
					],
					[
						65454.543,
						3,
						136.363632
					],
					[
						65590.91,
						0,
						136.363632
					],
					[
						65590.91,
						4,
						136.363632
					],
					[
						65727.27,
						5,
						136.363632
					],
					[
						65727.27,
						1,
						136.363632
					],
					[
						65863.63,
						4,
						136.363632
					],
					[
						65863.63,
						0,
						136.363632
					],
					[
						66000,
						3,
						136.363632
					],
					[
						66000,
						7,
						136.363632
					],
					[
						66136.36,
						0,
						136.363632
					],
					[
						66136.36,
						4,
						136.363632
					],
					[
						66272.73,
						5,
						136.363632
					],
					[
						66272.73,
						1,
						136.363632
					],
					[
						66409.0859,
						4,
						136.363632
					],
					[
						66409.0859,
						0,
						136.363632
					]
				],
				"mustHitSection": false
			},
			{
				"lengthInSteps": 16,
				"sectionNotes": [
					[
						66545.45,
						5,
						136.363632
					],
					[
						66545.45,
						1,
						136.363632
					],
					[
						66681.81,
						2,
						136.363632
					],
					[
						66681.81,
						6,
						136.363632
					],
					[
						66818.18,
						3,
						272.727264
					],
					[
						66818.18,
						7,
						272.727264
					],
					[
						67090.91,
						2,
						136.363632
					],
					[
						67090.91,
						6,
						136.363632
					],
					[
						67227.27,
						1,
						136.363632
					],
					[
						67227.27,
						5,
						136.363632
					],
					[
						67363.63,
						0,
						136.363632
					],
					[
						67363.63,
						4,
						136.363632
					],
					[
						67500,
						5,
						136.363632
					],
					[
						67500,
						1,
						136.363632
					]
				],
				"mustHitSection": true
			},
			{
				"lengthInSteps": 16,
				"sectionNotes": [
					[
						67636.36,
						0,
						0
					],
					[
						67704.55,
						1,
						0
					],
					[
						67772.73,
						2,
						0
					],
					[
						67840.91,
						3,
						0
					],
					[
						67909.0859,
						2,
						0
					],
					[
						67977.27,
						0,
						0
					],
					[
						68045.45,
						1,
						0
					],
					[
						68113.63,
						2,
						0
					],
					[
						68181.81,
						1,
						0
					],
					[
						68250,
						0,
						0
					],
					[
						68318.18,
						2,
						0
					],
					[
						68386.36,
						1,
						0
					],
					[
						68454.55,
						3,
						0
					],
					[
						68522.73,
						0,
						0
					],
					[
						68590.91,
						3,
						0
					],
					[
						68659.0859,
						0,
						0
					]
				],
				"mustHitSection": false
			},
			{
				"lengthInSteps": 16,
				"sectionNotes": [
					[
						68727.27,
						2,
						0
					],
					[
						68795.45,
						3,
						0
					],
					[
						68863.63,
						2,
						0
					],
					[
						68931.81,
						0,
						0
					],
					[
						69000,
						1,
						0
					],
					[
						69068.18,
						0,
						0
					],
					[
						69136.36,
						1,
						0
					],
					[
						69204.55,
						2,
						0
					],
					[
						69272.73,
						1,
						0
					],
					[
						69340.91,
						2,
						0
					],
					[
						69409.0859,
						1,
						0
					],
					[
						69477.27,
						0,
						0
					],
					[
						69545.45,
						3,
						0
					],
					[
						69613.63,
						1,
						204.545441
					]
				],
				"mustHitSection": false
			},
			{
				"lengthInSteps": 16,
				"sectionNotes": [
					[
						69818.18,
						0,
						0
					],
					[
						69886.36,
						1,
						0
					],
					[
						69954.55,
						2,
						0
					],
					[
						70022.73,
						3,
						0
					],
					[
						70090.91,
						2,
						0
					],
					[
						70159.0859,
						0,
						0
					],
					[
						70227.27,
						1,
						0
					],
					[
						70295.45,
						2,
						0
					],
					[
						70363.63,
						1,
						0
					],
					[
						70431.81,
						0,
						0
					],
					[
						70500,
						2,
						0
					],
					[
						70568.18,
						1,
						0
					],
					[
						70636.36,
						3,
						0
					],
					[
						70704.55,
						0,
						0
					],
					[
						70772.73,
						3,
						0
					],
					[
						70840.91,
						0,
						0
					]
				],
				"mustHitSection": true
			},
			{
				"lengthInSteps": 16,
				"sectionNotes": [
					[
						70909.0859,
						2,
						0
					],
					[
						70977.27,
						3,
						0
					],
					[
						71045.45,
						2,
						0
					],
					[
						71113.63,
						0,
						0
					],
					[
						71181.81,
						1,
						0
					],
					[
						71250,
						0,
						0
					],
					[
						71318.18,
						1,
						0
					],
					[
						71386.36,
						2,
						0
					],
					[
						71454.55,
						1,
						0
					],
					[
						71522.73,
						2,
						0
					],
					[
						71590.91,
						1,
						0
					],
					[
						71659.0859,
						0,
						0
					],
					[
						71727.27,
						3,
						0
					],
					[
						71795.45,
						1,
						204.545441
					]
				],
				"mustHitSection": true
			},
			{
				"lengthInSteps": 16,
				"sectionNotes": [
					[
						72000,
						3,
						0
					],
					[
						72068.18,
						2,
						0
					],
					[
						72136.36,
						0,
						0
					],
					[
						72204.55,
						2,
						0
					],
					[
						72272.73,
						0,
						0
					],
					[
						72340.91,
						2,
						0
					],
					[
						72409.0859,
						3,
						0
					],
					[
						72477.27,
						2,
						0
					],
					[
						72545.45,
						1,
						0
					],
					[
						72613.63,
						2,
						0
					],
					[
						72681.81,
						3,
						0
					],
					[
						72750,
						2,
						0
					],
					[
						72818.18,
						1,
						0
					],
					[
						72886.36,
						3,
						0
					],
					[
						72954.55,
						1,
						0
					],
					[
						73022.73,
						3,
						0
					]
				],
				"mustHitSection": false
			},
			{
				"lengthInSteps": 16,
				"sectionNotes": [
					[
						73090.91,
						2,
						136.363632
					],
					[
						73227.27,
						0,
						136.363632
					],
					[
						73363.63,
						2,
						136.363632
					],
					[
						73500,
						3,
						136.363632
					],
					[
						73636.36,
						2,
						0
					],
					[
						73704.55,
						3,
						0
					],
					[
						73772.73,
						2,
						0
					],
					[
						73840.91,
						0,
						0
					],
					[
						73909.0859,
						2,
						0
					],
					[
						73977.27,
						0,
						0
					],
					[
						74045.45,
						3,
						0
					],
					[
						74113.63,
						2,
						0
					]
				],
				"mustHitSection": false
			},
			{
				"lengthInSteps": 16,
				"sectionNotes": [
					[
						74181.81,
						3,
						0
					],
					[
						74250,
						2,
						0
					],
					[
						74318.18,
						0,
						0
					],
					[
						74386.36,
						2,
						0
					],
					[
						74454.55,
						0,
						0
					],
					[
						74522.73,
						2,
						0
					],
					[
						74590.91,
						3,
						0
					],
					[
						74659.0859,
						2,
						0
					],
					[
						74727.27,
						1,
						0
					],
					[
						74795.45,
						2,
						0
					],
					[
						74863.63,
						3,
						0
					],
					[
						74931.81,
						2,
						0
					],
					[
						75000,
						1,
						0
					],
					[
						75068.18,
						3,
						0
					],
					[
						75136.36,
						1,
						0
					],
					[
						75204.55,
						3,
						0
					]
				],
				"mustHitSection": true
			},
			{
				"lengthInSteps": 16,
				"sectionNotes": [
					[
						75272.73,
						2,
						136.363632
					],
					[
						75409.0859,
						0,
						136.363632
					],
					[
						75545.45,
						2,
						136.363632
					],
					[
						75681.81,
						3,
						136.363632
					],
					[
						75818.18,
						2,
						0
					],
					[
						75886.36,
						3,
						0
					],
					[
						75954.55,
						2,
						0
					],
					[
						76022.73,
						0,
						0
					],
					[
						76090.91,
						2,
						0
					],
					[
						76159.0859,
						0,
						0
					],
					[
						76227.27,
						3,
						0
					],
					[
						76295.45,
						2,
						0
					]
				],
				"mustHitSection": true
			},
			{
				"lengthInSteps": 16,
				"sectionNotes": [
					[
						76363.63,
						2,
						0
					],
					[
						76386.36,
						0,
						0
					],
					[
						76409.0859,
						2,
						0
					],
					[
						76431.81,
						3,
						0
					],
					[
						76454.55,
						2,
						0
					],
					[
						76477.27,
						3,
						0
					],
					[
						76500,
						0,
						0
					],
					[
						76522.73,
						2,
						0
					],
					[
						76545.45,
						0,
						0
					],
					[
						76568.18,
						1,
						0
					],
					[
						76590.91,
						0,
						0
					],
					[
						76613.63,
						2,
						0
					],
					[
						76636.36,
						3,
						0
					],
					[
						76659.0859,
						2,
						0
					],
					[
						76681.81,
						0,
						0
					],
					[
						76704.55,
						1,
						0
					],
					[
						76727.27,
						2,
						0
					],
					[
						76750,
						0,
						0
					],
					[
						76772.73,
						2,
						0
					],
					[
						76795.45,
						0,
						0
					],
					[
						76818.18,
						3,
						0
					],
					[
						76863.63,
						2,
						0
					],
					[
						76909.0859,
						0,
						136.363632
					],
					[
						77045.45,
						2,
						136.363632
					],
					[
						77181.81,
						3,
						136.363632
					],
					[
						77318.18,
						1,
						136.363632
					],
					[
						76840.909090909,
						-1,
						"Screen Shake",
						"2",
						"2"
					],
					[
						76772.7272727272,
						-1,
						"Screen Shake",
						"2",
						"2"
					],
					[
						76704.5454545454,
						-1,
						"Screen Shake",
						"2",
						"2"
					],
					[
						76636.3636363636,
						-1,
						"Screen Shake",
						"2",
						"2"
					],
					[
						76568.1818181817,
						-1,
						"Screen Shake",
						"2",
						"2"
					],
					[
						76499.9999999999,
						-1,
						"Screen Shake",
						"2",
						"2"
					],
					[
						76431.8181818181,
						-1,
						"Screen Shake",
						"2",
						"2"
					],
					[
						76363.6363636363,
						-1,
						"Screen Shake",
						"2",
						"2"
					]
				],
				"mustHitSection": false
			},
			{
				"lengthInSteps": 16,
				"sectionNotes": [
					[
						77454.55,
						2,
						136.363632
					],
					[
						77590.91,
						3,
						136.363632
					],
					[
						77727.27,
						2,
						136.363632
					],
					[
						77863.63,
						0,
						136.363632
					],
					[
						78000,
						2,
						136.363632
					],
					[
						78136.36,
						3,
						136.363632
					],
					[
						78272.73,
						2,
						0
					],
					[
						78340.91,
						1,
						0
					],
					[
						78409.0859,
						0,
						136.363632
					]
				],
				"mustHitSection": false
			},
			{
				"lengthInSteps": 16,
				"sectionNotes": [
					[
						78545.45,
						2,
						0
					],
					[
						78568.18,
						0,
						0
					],
					[
						78590.91,
						2,
						0
					],
					[
						78613.63,
						3,
						0
					],
					[
						78636.36,
						2,
						0
					],
					[
						78659.0859,
						3,
						0
					],
					[
						78681.81,
						0,
						0
					],
					[
						78704.55,
						2,
						0
					],
					[
						78727.27,
						0,
						0
					],
					[
						78750,
						1,
						0
					],
					[
						78772.73,
						0,
						0
					],
					[
						78795.45,
						2,
						0
					],
					[
						78818.18,
						3,
						0
					],
					[
						78840.91,
						2,
						0
					],
					[
						78863.63,
						0,
						0
					],
					[
						78886.36,
						1,
						0
					],
					[
						78909.0859,
						2,
						0
					],
					[
						78931.81,
						0,
						0
					],
					[
						78954.55,
						2,
						0
					],
					[
						78977.27,
						0,
						0
					],
					[
						79000,
						3,
						0
					],
					[
						79045.45,
						2,
						0
					],
					[
						79090.91,
						0,
						136.363632
					],
					[
						79227.27,
						2,
						136.363632
					],
					[
						79363.63,
						3,
						136.363632
					],
					[
						79500,
						1,
						136.363632
					],
					[
						78545.4545454545,
						-1,
						"Screen Shake",
						"2",
						"2"
					],
					[
						78613.6363636363,
						-1,
						"Screen Shake",
						"2",
						"2"
					],
					[
						78681.8181818181,
						-1,
						"Screen Shake",
						"2",
						"2"
					],
					[
						78749.9999999999,
						-1,
						"Screen Shake",
						"2",
						"2"
					],
					[
						78818.1818181817,
						-1,
						"Screen Shake",
						"2",
						"2"
					],
					[
						78886.3636363635,
						-1,
						"Screen Shake",
						"2",
						"2"
					],
					[
						78954.5454545454,
						-1,
						"Screen Shake",
						"2",
						"2"
					],
					[
						79022.7272727272,
						-1,
						"Screen Shake",
						"2",
						"2"
					]
				],
				"mustHitSection": true
			},
			{
				"lengthInSteps": 16,
				"sectionNotes": [
					[
						79636.36,
						2,
						136.363632
					],
					[
						79772.73,
						3,
						136.363632
					],
					[
						79909.0859,
						2,
						136.363632
					],
					[
						80045.45,
						0,
						136.363632
					],
					[
						80181.81,
						2,
						136.363632
					],
					[
						80318.18,
						3,
						136.363632
					],
					[
						80454.55,
						2,
						0
					],
					[
						80522.73,
						1,
						0
					],
					[
						80590.91,
						0,
						136.363632
					]
				],
				"mustHitSection": true
			},
			{
				"lengthInSteps": 16,
				"sectionNotes": [
					[
						80727.27,
						2,
						0
					],
					[
						80772.73,
						1,
						0
					],
					[
						80818.18,
						3,
						0
					],
					[
						80863.63,
						2,
						0
					],
					[
						80909.0859,
						0,
						0
					],
					[
						80954.55,
						1,
						0
					],
					[
						81000,
						2,
						0
					],
					[
						81045.45,
						3,
						0
					],
					[
						81090.91,
						1,
						0
					],
					[
						81136.36,
						3,
						0
					],
					[
						81181.81,
						2,
						0
					],
					[
						81227.27,
						3,
						0
					],
					[
						81272.73,
						1,
						0
					],
					[
						81318.18,
						3,
						0
					],
					[
						81363.63,
						0,
						0
					],
					[
						81431.81,
						3,
						0
					],
					[
						81500,
						2,
						0
					],
					[
						81545.45,
						0,
						0
					],
					[
						81590.91,
						3,
						0
					],
					[
						81636.36,
						1,
						0
					],
					[
						81681.81,
						2,
						0
					],
					[
						81727.27,
						3,
						0
					],
					[
						81772.73,
						0,
						0
					]
				],
				"mustHitSection": false
			},
			{
				"lengthInSteps": 16,
				"sectionNotes": [
					[
						81818.18,
						2,
						0
					],
					[
						81863.63,
						1,
						0
					],
					[
						81909.0859,
						3,
						0
					],
					[
						81954.54,
						2,
						0
					],
					[
						82000,
						0,
						0
					],
					[
						82045.45,
						1,
						0
					],
					[
						82090.91,
						2,
						0
					],
					[
						82136.36,
						3,
						0
					],
					[
						82181.81,
						1,
						0
					],
					[
						82227.27,
						3,
						0
					],
					[
						82272.73,
						2,
						0
					],
					[
						82318.18,
						3,
						0
					],
					[
						82363.63,
						1,
						0
					],
					[
						82409.0859,
						3,
						0
					],
					[
						82454.54,
						0,
						0
					],
					[
						82522.73,
						3,
						0
					],
					[
						82590.91,
						2,
						0
					],
					[
						82636.36,
						0,
						0
					],
					[
						82681.81,
						3,
						0
					],
					[
						82727.27,
						1,
						0
					],
					[
						82772.73,
						2,
						0
					],
					[
						82818.18,
						3,
						0
					],
					[
						82863.63,
						0,
						0
					]
				],
				"mustHitSection": true
			},
			{
				"lengthInSteps": 16,
				"sectionNotes": [
					[
						82909.0859,
						6,
						0
					],
					[
						82954.54,
						4,
						0
					],
					[
						83000,
						7,
						0
					],
					[
						83045.45,
						6,
						0
					],
					[
						83090.91,
						4,
						0
					],
					[
						83136.36,
						5,
						0
					],
					[
						83181.81,
						4,
						0
					],
					[
						83227.27,
						7,
						0
					],
					[
						83272.73,
						6,
						0
					],
					[
						83318.18,
						7,
						0
					],
					[
						83363.63,
						4,
						0
					],
					[
						83409.0859,
						7,
						0
					],
					[
						83454.54,
						2,
						0
					],
					[
						83500,
						0,
						0
					],
					[
						83545.45,
						3,
						0
					],
					[
						83590.91,
						2,
						0
					],
					[
						83636.36,
						0,
						0
					],
					[
						83681.81,
						1,
						0
					],
					[
						83727.27,
						0,
						0
					],
					[
						83772.73,
						3,
						0
					],
					[
						83818.18,
						2,
						0
					],
					[
						83863.63,
						3,
						0
					],
					[
						83909.0859,
						0,
						0
					],
					[
						83954.54,
						3,
						0
					]
				],
				"mustHitSection": true
			},
			{
				"lengthInSteps": 16,
				"sectionNotes": [
					[
						84000,
						6,
						0
					],
					[
						84045.45,
						5,
						0
					],
					[
						84090.91,
						7,
						0
					],
					[
						84136.36,
						6,
						0
					],
					[
						84181.81,
						4,
						0
					],
					[
						84227.27,
						5,
						0
					],
					[
						84272.73,
						6,
						0
					],
					[
						84318.18,
						7,
						0
					],
					[
						84363.63,
						4,
						0
					],
					[
						84409.0859,
						7,
						0
					],
					[
						84454.54,
						6,
						0
					],
					[
						84500,
						7,
						0
					],
					[
						84545.45,
						2,
						0
					],
					[
						84590.91,
						1,
						0
					],
					[
						84636.36,
						3,
						0
					],
					[
						84681.81,
						2,
						0
					],
					[
						84727.27,
						0,
						0
					],
					[
						84772.73,
						1,
						0
					],
					[
						84818.18,
						2,
						0
					],
					[
						84863.63,
						3,
						0
					],
					[
						84909.0859,
						0,
						0
					],
					[
						84954.54,
						3,
						0
					],
					[
						85000,
						2,
						0
					],
					[
						85045.45,
						3,
						0
					]
				],
				"mustHitSection": true
			},
			{
				"lengthInSteps": 16,
				"sectionNotes": [
					[
						85090.91,
						6,
						0
					],
					[
						85227.27,
						6,
						0
					],
					[
						85363.63,
						2,
						0
					],
					[
						85500,
						2,
						0
					],
					[
						85636.36,
						6,
						0
					],
					[
						85772.73,
						6,
						0
					],
					[
						85909.0859,
						2,
						0
					],
					[
						86045.45,
						2,
						0
					]
				],
				"mustHitSection": true
			},
			{
				"lengthInSteps": 16,
				"sectionNotes": [
					[
						86181.81,
						6,
						0
					],
					[
						86318.18,
						6,
						0
					],
					[
						86454.54,
						2,
						0
					],
					[
						86590.91,
						2,
						0
					],
					[
						86727.27,
						6,
						0
					],
					[
						86863.63,
						6,
						0
					],
					[
						87000,
						2,
						0
					],
					[
						87136.36,
						2,
						0
					]
				],
				"mustHitSection": true
			},
			{
				"lengthInSteps": 16,
				"sectionNotes": [
					[
						87272.73,
						6,
						0
					],
					[
						87272.73,
						2,
						0
					],
					[
						87409.0859,
						6,
						0
					],
					[
						87409.0859,
						2,
						0
					],
					[
						87545.45,
						6,
						0
					],
					[
						87545.45,
						2,
						0
					],
					[
						87681.81,
						6,
						0
					],
					[
						87681.81,
						2,
						0
					],
					[
						87818.18,
						6,
						0
					],
					[
						87818.18,
						2,
						0
					],
					[
						87886.36,
						6,
						0
					],
					[
						87886.36,
						2,
						0
					],
					[
						87954.54,
						6,
						0
					],
					[
						87954.54,
						2,
						0
					],
					[
						88022.73,
						6,
						0
					],
					[
						88022.73,
						2,
						0
					],
					[
						88068.18,
						6,
						0
					],
					[
						88068.18,
						2,
						0
					],
					[
						88113.63,
						6,
						0
					],
					[
						88113.63,
						2,
						0
					],
					[
						88159.0859,
						6,
						0
					],
					[
						88159.0859,
						2,
						0
					],
					[
						88204.54,
						6,
						0
					],
					[
						88204.54,
						2,
						0
					],
					[
						88250,
						6,
						0
					],
					[
						88250,
						2,
						0
					],
					[
						88295.45,
						6,
						0
					],
					[
						88295.45,
						2,
						0
					],
					[
						88340.91,
						6,
						0
					],
					[
						88340.91,
						2,
						0
					]
				],
				"mustHitSection": true
			},
			{
				"lengthInSteps": 16,
				"sectionNotes": [
					[
						88363.63,
						0,
						1090.909
					],
					[
						88363.63,
						2,
						1090.909
					],
					[
						88363.63,
						1,
						1090.909
					],
					[
						88363.63,
						3,
						1090.909
					]
				],
				"mustHitSection": false
			},
			{
				"lengthInSteps": 16,
				"sectionNotes": [
					[
						89454.54,
						4,
						818.181763
					],
					[
						89454.54,
						0,
						0
					],
					[
						89545.45,
						3,
						0
					],
					[
						89636.36,
						1,
						0
					],
					[
						89727.27,
						0,
						0
					],
					[
						89818.18,
						2,
						0
					],
					[
						89909.0859,
						3,
						0
					],
					[
						90000,
						0,
						0
					],
					[
						90090.91,
						3,
						0
					],
					[
						90181.81,
						2,
						0
					],
					[
						90272.73,
						5,
						272.727264
					],
					[
						90272.73,
						0,
						0
					],
					[
						90363.63,
						3,
						0
					],
					[
						90454.54,
						2,
						0
					]
				],
				"mustHitSection": false
			},
			{
				"lengthInSteps": 16,
				"sectionNotes": [
					[
						90545.45,
						7,
						0
					],
					[
						90545.45,
						0,
						818.181763
					],
					[
						90636.36,
						6,
						0
					],
					[
						90727.27,
						4,
						0
					],
					[
						90818.18,
						6,
						0
					],
					[
						90909.0859,
						7,
						0
					],
					[
						91000,
						6,
						0
					],
					[
						91090.91,
						5,
						0
					],
					[
						91181.81,
						4,
						0
					],
					[
						91272.73,
						5,
						0
					],
					[
						91363.63,
						2,
						0
					],
					[
						91363.63,
						6,
						0
					],
					[
						91454.54,
						1,
						0
					],
					[
						91454.54,
						7,
						0
					],
					[
						91545.45,
						6,
						0
					],
					[
						91545.45,
						0,
						0
					]
				],
				"mustHitSection": true
			},
			{
				"lengthInSteps": 16,
				"sectionNotes": [
					[
						91636.36,
						6,
						818.181763
					],
					[
						91636.36,
						1,
						0
					],
					[
						91727.27,
						0,
						0
					],
					[
						91818.18,
						1,
						0
					],
					[
						91909.0859,
						2,
						0
					],
					[
						92000,
						1,
						0
					],
					[
						92090.91,
						2,
						0
					],
					[
						92181.81,
						0,
						0
					],
					[
						92272.73,
						3,
						0
					],
					[
						92363.63,
						0,
						0
					],
					[
						92454.54,
						3,
						0
					],
					[
						92454.54,
						7,
						272.727264
					],
					[
						92545.45,
						2,
						0
					],
					[
						92636.36,
						3,
						0
					]
				],
				"mustHitSection": false
			},
			{
				"lengthInSteps": 16,
				"sectionNotes": [
					[
						92727.27,
						5,
						0
					],
					[
						92727.27,
						2,
						818.181763
					],
					[
						92818.18,
						7,
						0
					],
					[
						92909.0859,
						5,
						0
					],
					[
						93000,
						6,
						0
					],
					[
						93090.91,
						5,
						0
					],
					[
						93181.81,
						6,
						0
					],
					[
						93272.73,
						4,
						0
					],
					[
						93363.63,
						6,
						0
					],
					[
						93454.54,
						4,
						0
					],
					[
						93545.45,
						0,
						0
					],
					[
						93545.45,
						5,
						0
					],
					[
						93636.36,
						3,
						0
					],
					[
						93636.36,
						7,
						0
					],
					[
						93727.27,
						4,
						0
					],
					[
						93727.27,
						1,
						0
					]
				],
				"mustHitSection": true
			},
			{
				"lengthInSteps": 16,
				"sectionNotes": [
					[
						93818.18,
						0,
						818.181763
					],
					[
						93818.18,
						4,
						0
					],
					[
						93909.0859,
						6,
						0
					],
					[
						94000,
						7,
						0
					],
					[
						94090.91,
						4,
						0
					],
					[
						94181.81,
						7,
						0
					],
					[
						94272.73,
						6,
						0
					],
					[
						94363.63,
						4,
						0
					],
					[
						94454.54,
						7,
						0
					],
					[
						94545.45,
						6,
						0
					],
					[
						94636.36,
						1,
						272.727264
					],
					[
						94636.36,
						7,
						0
					],
					[
						94727.27,
						6,
						0
					],
					[
						94818.18,
						4,
						0
					]
				],
				"mustHitSection": false
			},
			{
				"lengthInSteps": 16,
				"sectionNotes": [
					[
						94909.0859,
						4,
						818.181763
					],
					[
						94909.0859,
						2,
						0
					],
					[
						95000,
						3,
						0
					],
					[
						95090.91,
						2,
						0
					],
					[
						95181.81,
						1,
						0
					],
					[
						95272.73,
						0,
						0
					],
					[
						95363.63,
						1,
						0
					],
					[
						95454.54,
						2,
						0
					],
					[
						95545.45,
						3,
						0
					],
					[
						95636.36,
						2,
						0
					],
					[
						95727.27,
						6,
						0
					],
					[
						95727.27,
						1,
						0
					],
					[
						95818.18,
						5,
						0
					],
					[
						95818.18,
						0,
						0
					],
					[
						95909.0859,
						4,
						0
					],
					[
						95909.0859,
						1,
						0
					]
				],
				"mustHitSection": true
			},
			{
				"lengthInSteps": 16,
				"sectionNotes": [
					[
						96000,
						2,
						818.181763
					],
					[
						96000,
						6,
						0
					],
					[
						96090.91,
						5,
						0
					],
					[
						96181.81,
						6,
						0
					],
					[
						96272.73,
						4,
						0
					],
					[
						96363.63,
						7,
						0
					],
					[
						96454.54,
						4,
						0
					],
					[
						96545.45,
						7,
						0
					],
					[
						96636.36,
						6,
						0
					],
					[
						96727.27,
						7,
						0
					],
					[
						96818.18,
						3,
						272.727264
					],
					[
						96818.18,
						5,
						0
					],
					[
						96909.0859,
						7,
						0
					],
					[
						97000,
						5,
						0
					]
				],
				"mustHitSection": false
			},
			{
				"lengthInSteps": 16,
				"sectionNotes": [
					[
						97090.91,
						6,
						818.181763
					],
					[
						97090.91,
						2,
						0
					],
					[
						97181.81,
						1,
						0
					],
					[
						97272.73,
						2,
						0
					],
					[
						97363.63,
						0,
						0
					],
					[
						97454.54,
						2,
						0
					],
					[
						97545.45,
						0,
						0
					],
					[
						97636.36,
						1,
						0
					],
					[
						97727.27,
						3,
						0
					],
					[
						97818.18,
						0,
						0
					],
					[
						97909.0859,
						3,
						0
					],
					[
						98000,
						2,
						0
					],
					[
						98090.91,
						1,
						0
					]
				],
				"mustHitSection": true
			},
			{
				"bounce": false,
				"circle": false,
				"fadein": false,
				"fadeout": false,
				"altAnim": false,
				"cancel": false,
				"cameraflip": false,
				"mustHitSection": true,
				"lengthInSteps": 16,
				"typeOfSection": 0,
				"sectionNotes": [],
				"camerabounce": false,
				"cameracancel": false,
				"changeBPM": false,
				"bpm": 220
			},
			{
				"lengthInSteps": 16,
				"typeOfSection": 0,
				"sectionNotes": [],
				"altAnim": false,
				"bpm": 220,
				"changeBPM": false,
				"mustHitSection": true
			},
			{
				"lengthInSteps": 16,
				"typeOfSection": 0,
				"sectionNotes": [],
				"altAnim": false,
				"bpm": 220,
				"changeBPM": false,
				"mustHitSection": true
			},
			{
				"sectionNotes": [],
				"typeOfSection": 0,
				"lengthInSteps": 16,
				"altAnim": false,
				"mustHitSection": true,
				"changeBPM": false,
				"bpm": 220
			},
			{
				"sectionNotes": [],
				"typeOfSection": 0,
				"lengthInSteps": 16,
				"altAnim": false,
				"mustHitSection": true,
				"changeBPM": false,
				"bpm": 220
			},
			{
				"lengthInSteps": 16,
				"altAnim": false,
				"typeOfSection": 0,
				"sectionNotes": [],
				"bpm": 220,
				"changeBPM": false,
				"mustHitSection": true
			},
			{
				"lengthInSteps": 16,
				"altAnim": false,
				"typeOfSection": 0,
				"sectionNotes": [],
				"bpm": 220,
				"changeBPM": false,
				"mustHitSection": true
			}
		],
		"player3": "gf",
		"song": "Dahard",
		"stage": "ghostyStage",
		"validScore": true,
		"needsVoices": true,
		"speed": 3,
		"bpm": 220
	}
}